rfmizer/__init__.py
rfmizer/action.py
rfmizer/admin.py
rfmizer/apps.py
rfmizer/fixtures.py
rfmizer/forms.py
rfmizer/models.py
rfmizer/sms.py
rfmizer/tasks.py
rfmizer/test_action.py
rfmizer/test_tasks.py
rfmizer/tests_forms.py
rfmizer/tests_models.py
rfmizer/tests_views.py
rfmizer/urls.py
rfmizer/validators.py
rfmizer/views.py
rfmizer/fixtures/corrupt_data_testsheet.csv
rfmizer/fixtures/fixtures.json
rfmizer/fixtures/testdbsheet.csv
rfmizer/migrations/0001_initial.py
rfmizer/migrations/__init__.py
rfmizer/static/assets/css/fontawesome-all.min.css
rfmizer/static/assets/css/main.css
rfmizer/static/assets/css/noscript.css
rfmizer/static/assets/css/images/intro.svg
rfmizer/static/assets/js/breakpoints.min.js
rfmizer/static/assets/js/browser.min.js
rfmizer/static/assets/js/jquery.min.js
rfmizer/static/assets/js/jquery.scrollex.min.js
rfmizer/static/assets/js/jquery.scrolly.min.js
rfmizer/static/assets/js/main.js
rfmizer/static/assets/js/util.js
rfmizer/static/assets/sass/main.scss
rfmizer/static/assets/sass/noscript.scss
rfmizer/static/assets/sass/base/_page.scss
rfmizer/static/assets/sass/base/_reset.scss
rfmizer/static/assets/sass/base/_typography.scss
rfmizer/static/assets/sass/components/_actions.scss
rfmizer/static/assets/sass/components/_box.scss
rfmizer/static/assets/sass/components/_button.scss
rfmizer/static/assets/sass/components/_contact.scss
rfmizer/static/assets/sass/components/_features.scss
rfmizer/static/assets/sass/components/_form.scss
rfmizer/static/assets/sass/components/_icon.scss
rfmizer/static/assets/sass/components/_icons.scss
rfmizer/static/assets/sass/components/_image.scss
rfmizer/static/assets/sass/components/_list.scss
rfmizer/static/assets/sass/components/_menu.scss
rfmizer/static/assets/sass/components/_row.scss
rfmizer/static/assets/sass/components/_section.scss
rfmizer/static/assets/sass/components/_split.scss
rfmizer/static/assets/sass/components/_spotlights.scss
rfmizer/static/assets/sass/components/_table.scss
django_rfmizer-0.2.dist-info/LICENSE
django_rfmizer-0.2.dist-info/METADATA
django_rfmizer-0.2.dist-info/WHEEL
django_rfmizer-0.2.dist-info/top_level.txt
django_rfmizer-0.2.dist-info/RECORD
