Metadata-Version: 2.1
Name: django-rfmizer
Version: 0.2
Summary: A django based automaton do a sms messaging.
Home-page: UNKNOWN
Author: Vladimir
Author-email: JunglistMNSQ@gmqil.com
License: BSD-3-Clause  # Example license
Platform: UNKNOWN
Classifier: Environment :: Web Environment
Classifier: Framework :: Django :: 3.1
Classifier: Intended Audience :: Customer Service
Classifier: License :: OSI Approved :: BSD License
Classifier: Operating System :: OS Independent
Classifier: Programming Language :: Python :: 3.6
Classifier: Natural Language :: Russian
Requires-Dist: amqp (==5.0.1)
Requires-Dist: asgiref (==3.2.10)
Requires-Dist: billiard (==3.6.3.0)
Requires-Dist: celery (==5.0.0)
Requires-Dist: certifi (==2020.6.20)
Requires-Dist: chardet (==3.0.4)
Requires-Dist: click-didyoumean (==0.0.3)
Requires-Dist: click-repl (==0.1.6)
Requires-Dist: click (==7.1.2)
Requires-Dist: django-celery-beat (==2.0.0)
Requires-Dist: django-extensions (==3.0.9)
Requires-Dist: django-fixture-magic (==0.1.5)
Requires-Dist: django-multiselectfield (==0.1.12)
Requires-Dist: django-phonenumber-field[phonenumbers] (==5.0.0)
Requires-Dist: django-timezone-field (==4.0)
Requires-Dist: django-uuslug (==1.2.0)
Requires-Dist: django (==3.1.2)
Requires-Dist: future (==0.18.2)
Requires-Dist: idna (==2.10)
Requires-Dist: kombu (==5.0.2)
Requires-Dist: mock (==4.0.2)
Requires-Dist: phonenumbers (==8.12.10)
Requires-Dist: prompt-toolkit (==3.0.7)
Requires-Dist: psycopg2-binary (==2.8.6)
Requires-Dist: python-crontab (==2.5.1)
Requires-Dist: python-dateutil (==2.8.1)
Requires-Dist: python-slugify (==4.0.1)
Requires-Dist: pytz (==2020.1)
Requires-Dist: redis (==3.5.3)
Requires-Dist: requests (==2.24.0)
Requires-Dist: six (==1.15.0)
Requires-Dist: sqlparse (==0.4.1)
Requires-Dist: text-unidecode (==1.3)
Requires-Dist: urllib3 (==1.25.10)
Requires-Dist: vine (==5.0.0)
Requires-Dist: wcwidth (==0.2.5)
